rxdb_dataframe/__init__.py
rxdb_dataframe/frontend/.eslintignore
rxdb_dataframe/frontend/.eslintrc.json
rxdb_dataframe/frontend/build/assets/data/col.dump.json
rxdb_dataframe/frontend/build/assets/data/db.dump.json
rxdb_dataframe/frontend/build/assets/data/todo.schema.json
rxdb_dataframe/frontend/build/index.html
rxdb_dataframe/frontend/build/index.js
rxdb_dataframe/frontend/build/index.js.map
rxdb_dataframe/frontend/index.html
rxdb_dataframe/frontend/project.json
rxdb_dataframe/frontend/public/assets/data/col.dump.json
rxdb_dataframe/frontend/public/assets/data/db.dump.json
rxdb_dataframe/frontend/public/assets/data/todo.schema.json
rxdb_dataframe/frontend/src/lib/RxDBDataframe.tsx
rxdb_dataframe/frontend/src/lib/RxDBDataframeArgs.ts
rxdb_dataframe/frontend/src/lib/useEditingState.ts
rxdb_dataframe/frontend/src/lib/useNullableRenderData.ts
rxdb_dataframe/frontend/src/main.tsx
rxdb_dataframe/frontend/tsconfig.app.json
rxdb_dataframe/frontend/tsconfig.json
rxdb_dataframe/frontend/tsconfig.spec.json
rxdb_dataframe/frontend/vite.config.ts
rxdb_dataframe/test___init__.py
streamlit_rxdb_dataframe-0.1.0.dist-info/LICENSE
streamlit_rxdb_dataframe-0.1.0.dist-info/METADATA
streamlit_rxdb_dataframe-0.1.0.dist-info/WHEEL
streamlit_rxdb_dataframe-0.1.0.dist-info/RECORD
