Metadata-Version: 2.1
Name: streamlit-rxdb-dataframe
Version: 0.1.0
Summary: Custom streamlit component connecting local browser indexedDB database as RxDB collection as dataframe
Home-page: https://github.com/voznik/ngx-odm
License: MIT
Keywords: streamlit,indexedDB,RxDB,browser,connection,dataframe
Author: voznik
Author-email: mrvoznik@gmail.com
Requires-Python: >=3.10,<4.0
Classifier: License :: OSI Approved :: MIT License
Classifier: Programming Language :: Python :: 3
Classifier: Programming Language :: Python :: 3.10
Classifier: Programming Language :: Python :: 3.11
Classifier: Programming Language :: Python :: 3.12
Requires-Dist: jsonschema (>=4.21.1,<5.0.0)
Requires-Dist: pandas (>=2.2.1,<3.0.0)
Requires-Dist: playwright (>=1.41.2,<2.0.0)
Requires-Dist: pytest-playwright (>=0.4.4,<0.5.0)
Requires-Dist: streamlit (>=1.31.0,<2.0.0)
Project-URL: Repository, https://github.com/voznik/ngx-odm
